leatherman/__init__.py
leatherman/asyncrequests.py
leatherman/cfg.py
leatherman/config.py
leatherman/dbg.py
leatherman/dictionary.py
leatherman/friendly.py
leatherman/function.py
leatherman/fuzzy.py
leatherman/git.py
leatherman/importer.py
leatherman/isinstance.py
leatherman/json.py
leatherman/leatherman.py
leatherman/newline.py
leatherman/output.py
leatherman/pki.py
leatherman/repr.py
leatherman/shell.py
leatherman/sift.py
leatherman/singleton.py
leatherman/timestamp.py
leatherman/url.py
leatherman/version.py
leatherman/yaml.py
leatherman-0.2.0.dist-info/AUTHORS.rst
leatherman-0.2.0.dist-info/LICENSE
leatherman-0.2.0.dist-info/METADATA
leatherman-0.2.0.dist-info/WHEEL
leatherman-0.2.0.dist-info/RECORD
