Metadata-Version: 2.3
Name: leatherman
Version: 0.2.0
Summary: helpful multi tool
License: MIT
Keywords: leatherman
Author: Scott A. Idler
Author-email: scott.a.idler@gmail.com
Requires-Python: >=3.12,<4.0
Classifier: License :: OSI Approved :: MIT License
Classifier: Programming Language :: Python :: 3
Classifier: Programming Language :: Python :: 3.12
Classifier: Programming Language :: Python :: 3.13
Project-URL: Repository, https://github.com/scottidler/leatherman
